hud/__init__.py
hud/client.py
hud/env.py
hud/gym.py
hud/run.py
hud/settings.py
hud/adapters/__init__.py
hud/adapters/claude/__init__.py
hud/adapters/claude/adapter.py
hud/adapters/common/__init__.py
hud/adapters/common/adapter.py
hud/adapters/common/types.py
hud/server/__init__.py
hud/server/requests.py
hud/utils/__init__.py
hud/utils/config.py
hud/py.typed
hud_so-0.1.0.dist-info/METADATA
hud_so-0.1.0.dist-info/WHEEL
hud_so-0.1.0.dist-info/licenses/LICENSE
hud_so-0.1.0.dist-info/RECORD
