Metadata-Version: 2.4
Name: hud-so
Version: 0.1.0
Summary: SDK for the HUD evaluation platform.
Project-URL: Homepage, https://github.com/humanuniondata/hud-so
Project-URL: Bug Tracker, https://github.com/humanuniondata/hud-so/issues
Project-URL: Documentation, https://docs.hud.so
Author-email: Human Union Data SDK <founders@hud.so>
License: MIT License
License-File: LICENSE
Classifier: Development Status :: 4 - Beta
Classifier: Intended Audience :: Developers
Classifier: Programming Language :: Python :: 3
Classifier: Programming Language :: Python :: 3.9
Classifier: Programming Language :: Python :: 3.10
Classifier: Programming Language :: Python :: 3.11
Classifier: Programming Language :: Python :: 3.12
Classifier: Programming Language :: Python :: 3.13
Requires-Python: <3.14,>=3.9
Requires-Dist: eval-type-backport>=0.2.2
Requires-Dist: httpx<1,>=0.23.0
Requires-Dist: pillow<12,>=11
Requires-Dist: pydantic-settings<3,>=2
Requires-Dist: pydantic<3,>=2
Provides-Extra: dev
Requires-Dist: anthropic; extra == 'dev'
Requires-Dist: ipykernel; extra == 'dev'
Requires-Dist: ipython<9; extra == 'dev'
Requires-Dist: jupyter-client; extra == 'dev'
Requires-Dist: jupyter-core; extra == 'dev'
Requires-Dist: openai; extra == 'dev'
Requires-Dist: pyright==1.1.364; extra == 'dev'
Requires-Dist: pytest<9,>=8.1.1; extra == 'dev'
Requires-Dist: ruff==0.9.8; extra == 'dev'
